databasemodels/__init__.py
databasemodels/columns.py
databasemodels/connection.py
databasemodels/datatypes.py
databasemodels/exceptions.py
databasemodels/helper.py
databasemodels/protocols.py
databasemodels/py.typed
databasemodels/representations.py
databasemodels/version.py
databasemodels/wrapper.py
databasemodels-1.11.1.dist-info/LICENSE.txt
databasemodels-1.11.1.dist-info/METADATA
databasemodels-1.11.1.dist-info/WHEEL
databasemodels-1.11.1.dist-info/top_level.txt
databasemodels-1.11.1.dist-info/RECORD
