Metadata-Version: 2.1
Name: databasemodels
Version: 1.11.1
Summary: Python class decorator that creates a database representation of a class and vice versa, a lightweight ORM.
Home-page: https://github.com/HazelTheWitch/DatabaseModels
Author: Hazel Rella
Author-email: hazelrella11@gmail.com
License: MIT
Platform: UNKNOWN
Classifier: Development Status :: 5 - Production/Stable
Classifier: Intended Audience :: Developers
Classifier: License :: OSI Approved :: MIT License
Classifier: Natural Language :: English
Classifier: Programming Language :: Python :: 3 :: Only
Classifier: Programming Language :: Python :: 3.7
Classifier: Programming Language :: Python :: 3.8
Classifier: Programming Language :: Python :: 3.9
Classifier: Programming Language :: Python :: 3.10
Classifier: Programming Language :: Python :: 3.11
Requires-Python: >=3.7, <4
Requires-Dist: psycopg
Requires-Dist: psycopg-binary
Requires-Dist: iso8601
Requires-Dist: typing-extensions
